README.md
setup.cfg
setup.py
aiostorage/__init__.py
aiostorage/blob_storage.py
aiostorage/exceptions.py
aiostorage.egg-info/PKG-INFO
aiostorage.egg-info/SOURCES.txt
aiostorage.egg-info/dependency_links.txt
aiostorage.egg-info/requires.txt
aiostorage.egg-info/top_level.txt
aiostorage/providers/__init__.py
aiostorage/providers/backblaze.py
aiostorage/providers/exceptions.py
aiostorage/tests/__init__.py
aiostorage/tests/test_blob_storage.py
aiostorage/tests/providers/__init__.py
aiostorage/tests/providers/test_backblaze.py
aiostorage/tests/providers/apis/__init__.py
aiostorage/tests/providers/apis/test_backblaze_api.py