Metadata-Version: 1.1
Name: aiostorage
Version: 0.1.16
Summary: Asynchronous object storage
Home-page: https://github.com/family-guy/aiostorage.git
Author: Guy King
Author-email: grking8@gmail.com
License: MIT
Project-URL: Wiki, https://family-guy.github.io/aiostorage-wiki/
Project-URL: Source, https://github.com/family-guy/aiostorage.git
Project-URL: Tracker, https://github.com/family-guy/aiostorage/issues
Project-URL: Documentation, http://aiostorage.readthedocs.io/
Platform: UNKNOWN
Classifier: Development Status :: 1 - Planning
Classifier: Intended Audience :: Developers
Classifier: Programming Language :: Python :: 3.6
